bugtodo/__init__.py
bugtodo/cli.py
bugtodo/services/__init__.py
bugtodo/services/base.py
bugtodo/services/gitlab.py
bugtodo/services/jira.py
bugtodo/services/taiga.py
bugtodo-0.2.1.dist-info/METADATA
bugtodo-0.2.1.dist-info/WHEEL
bugtodo-0.2.1.dist-info/entry_points.txt
bugtodo-0.2.1.dist-info/top_level.txt
bugtodo-0.2.1.dist-info/RECORD
